zenui/__init__.py
zenui/app.py
zenui/cli.py
zenui/compiler.py
zenui/component.py
zenui/router.py
zenui/tags.py
zenui/zenui_dom.py
zenui-1.0.2.dist-info/LICENSE
zenui-1.0.2.dist-info/METADATA
zenui-1.0.2.dist-info/WHEEL
zenui-1.0.2.dist-info/top_level.txt
zenui-1.0.2.dist-info/RECORD
